tucquery/__init__.py
tucquery/joints.py
tucquery-0.0.2.dist-info/licenses/LICENSE
tucquery-0.0.2.dist-info/METADATA
tucquery-0.0.2.dist-info/WHEEL
tucquery-0.0.2.dist-info/top_level.txt
tucquery-0.0.2.dist-info/RECORD
