Metadata-Version: 2.4
Name: tucquery
Version: 0.0.2
Summary: The Useful CAD oficial expansion to Cadquery
Home-page: https://github.com/The-Useful-CAD/tucquery.git
Author: The Useful CAD LLC
Author-email: contact@theusefulcad.com
License-File: LICENSE
Dynamic: author
Dynamic: author-email
Dynamic: home-page
Dynamic: license-file
Dynamic: summary
